torchstreamer/__init__.py
torchstreamer/audio.py
torchstreamer/core.py
torch_streamer-0.0.2.dist-info/LICENSE
torch_streamer-0.0.2.dist-info/METADATA
torch_streamer-0.0.2.dist-info/WHEEL
torch_streamer-0.0.2.dist-info/top_level.txt
torch_streamer-0.0.2.dist-info/RECORD
