Metadata-Version: 2.1
Name: torch-streamer
Version: 0.0.2
Summary: Streaming convolutions for PyTorch
Author-email: "Brent M. Spell" <brent@brentspell.com>
License: MIT License
Project-URL: Homepage, https://github.com/brentspell/torch-streamer
Classifier: License :: OSI Approved :: MIT License
Classifier: Programming Language :: Python
Classifier: Programming Language :: Python :: 3
Requires-Python: >=3.10
License-File: LICENSE
Requires-Dist: torch
Requires-Dist: torchaudio
Provides-Extra: dev
Requires-Dist: build ; extra == 'dev'
Requires-Dist: mypy ; extra == 'dev'
Requires-Dist: pre-commit ; extra == 'dev'
Requires-Dist: pytest-watch ; extra == 'dev'
Requires-Dist: ruff ; extra == 'dev'
Requires-Dist: setuptools ; extra == 'dev'
Requires-Dist: twine ; extra == 'dev'
Requires-Dist: wheel ; extra == 'dev'
Requires-Dist: coveralls ; extra == 'dev'
Requires-Dist: hypothesis ; extra == 'dev'
Requires-Dist: pytest ; extra == 'dev'
Requires-Dist: pytest-benchmark ; extra == 'dev'
Requires-Dist: pytest-cov ; extra == 'dev'
Provides-Extra: docs
Requires-Dist: mkdocs ~=1.6 ; extra == 'docs'
Requires-Dist: mkdocstrings[python] ~=0.25 ; extra == 'docs'
